pyStFTP/__init__.py
pyStFTP/pyStFTP.py
pyStFtp-0.0.1.dist-info/LICENSE.md
pyStFtp-0.0.1.dist-info/METADATA
pyStFtp-0.0.1.dist-info/WHEEL
pyStFtp-0.0.1.dist-info/top_level.txt
pyStFtp-0.0.1.dist-info/RECORD
