Metadata-Version: 2.1
Name: pyStFtp
Version: 0.0.1
Summary: A cutom libaray to help in doing sfpt
Author-email: Mickael Eriksson <mickael@mickenet.com>
Project-URL: Homepage, https://github.com/MickaelE/pyStFtp.git
Project-URL: Bug Tracker, https://github.com/MickaelE/pyStFtp/issues
Classifier: Programming Language :: Python :: 3
Classifier: License :: OSI Approved :: MIT License
Classifier: Operating System :: OS Independent
Requires-Python: >=3.7
License-File: LICENSE.md
